mcquery/__init__.py
mcquery/query.py
mcquery-0.1.0.dist-info/LICENSE
mcquery-0.1.0.dist-info/METADATA
mcquery-0.1.0.dist-info/WHEEL
mcquery-0.1.0.dist-info/entry_points.txt
mcquery-0.1.0.dist-info/top_level.txt
mcquery-0.1.0.dist-info/RECORD
