Metadata-Version: 2.1
Name: mcquery
Version: 0.1.0
Summary: Query tool for Minecraft: Bedrock Edition servers.
Home-page: https://github.com/w-gao/py-mcpe-query
Author: w-gao
Author-email: me@wlgao.com
License: MIT
Keywords: minecraft bedrock mcpe mcbe mcpeserver mcbeserver
Platform: UNKNOWN
Classifier: Development Status :: 3 - Alpha
Classifier: Environment :: Console
Classifier: Intended Audience :: Developers
Classifier: Intended Audience :: System Administrators
Classifier: License :: OSI Approved :: MIT License
Classifier: Natural Language :: English
Classifier: Programming Language :: Python :: 3.6
Classifier: Topic :: Software Development :: Libraries :: Python Modules
Classifier: Topic :: System :: Networking
Requires-Python: >=3.6
